CHANGES.rst
MANIFEST.in
README.rst
setup.py
pyramid_skue/__init__.py
pyramid_skue/errors.py
pyramid_skue/http.py
pyramid_skue/utils.py
pyramid_skue.egg-info/PKG-INFO
pyramid_skue.egg-info/SOURCES.txt
pyramid_skue.egg-info/dependency_links.txt
pyramid_skue.egg-info/not-zip-safe
pyramid_skue.egg-info/requires.txt
pyramid_skue.egg-info/top_level.txt
pyramid_skue/json/__init__.py
pyramid_skue/json/utils.py
pyramid_skue/rest/__init__.py
pyramid_skue/rest/api.py
pyramid_skue/rest/resources.py