Metadata-Version: 1.1
Name: pyramid-skue
Version: 0.1.0
Summary: pyramid_skue
Home-page: https://github.com/kipanshi/pyramid_skue
Author: Cyril Panshine
Author-email: kipanshi@gmail.com
License: UNKNOWN
Keywords: web pyramid pylons rest api
Platform: UNKNOWN
Classifier: Programming Language :: Python
Classifier: Programming Language :: Python :: 2
Classifier: Framework :: Pyramid
Classifier: Topic :: Internet :: WWW/HTTP
